jwt_email_auth/__init__.py
jwt_email_auth/apps.py
jwt_email_auth/authentication.py
jwt_email_auth/definition.py
jwt_email_auth/exceptions.py
jwt_email_auth/fields.py
jwt_email_auth/models.py
jwt_email_auth/permissions.py
jwt_email_auth/py.typed
jwt_email_auth/rotation/__init__.py
jwt_email_auth/rotation/apps.py
jwt_email_auth/rotation/migrations/0001_initial.py
jwt_email_auth/rotation/migrations/__init__.py
jwt_email_auth/rotation/models.py
jwt_email_auth/schema.py
jwt_email_auth/serializers.py
jwt_email_auth/settings.py
jwt_email_auth/tokens.py
jwt_email_auth/typing.py
jwt_email_auth/utils.py
jwt_email_auth/views.py
jwt_email_auth-0.11.6.dist-info/LICENSE
jwt_email_auth-0.11.6.dist-info/METADATA
jwt_email_auth-0.11.6.dist-info/WHEEL
jwt_email_auth-0.11.6.dist-info/RECORD
