Metadata-Version: 2.3
Name: jwt-email-auth
Version: 0.11.6
Summary: JWT authentication from email login codes.
License: MIT
Keywords: django,djangorestframework,drf,email,code,login,jwt,auth,authentication
Author: Matti Lamppu
Author-email: lamppu.matti.akseli@gmail.com
Requires-Python: >=3.10,<4
Classifier: Environment :: Web Environment
Classifier: Framework :: Django
Classifier: Programming Language :: Python
Classifier: Programming Language :: Python :: 3
Classifier: Programming Language :: Python :: 3 :: Only
Classifier: Programming Language :: Python :: 3.10
Classifier: Programming Language :: Python :: 3.11
Classifier: Programming Language :: Python :: 3.12
Classifier: Programming Language :: Python :: 3.13
Classifier: Framework :: Django :: 4.2
Classifier: Framework :: Django :: 5.0
Classifier: Framework :: Django :: 5.1
Classifier: Intended Audience :: Developers
Classifier: Natural Language :: English
Requires-Dist: Django (>=4.2)
Requires-Dist: PyJWT (>=2.3.0)
Requires-Dist: PyYAML (>=5.4.1)
Requires-Dist: cffi (>=1.15.0)
Requires-Dist: cryptography (>=36.0.0)
Requires-Dist: django-ipware (>=4.0.0)
Requires-Dist: django-settings-holder (>=0.2.2)
Requires-Dist: djangorestframework (>=3.12.0)
Requires-Dist: uritemplate (>=4.1.1)
